MarkdownJiandanDeShijie/README.md
MarkdownJiandanDeShijie/__init__.py
MarkdownJiandanDeShijie/__main__.py
MarkdownJiandanDeShijie/file.epub
MarkdownJiandanDeShijie/index.html
MarkdownJiandanDeShijie/css/__init__.py
MarkdownJiandanDeShijie/css/annotations.css
MarkdownJiandanDeShijie/css/main.css
MarkdownJiandanDeShijie/css/normalize.css
MarkdownJiandanDeShijie/css/popup.css
MarkdownJiandanDeShijie/font/__init__.py
MarkdownJiandanDeShijie/font/fontello.eot
MarkdownJiandanDeShijie/font/fontello.svg
MarkdownJiandanDeShijie/font/fontello.ttf
MarkdownJiandanDeShijie/font/fontello.woff
MarkdownJiandanDeShijie/img/__init__.py
MarkdownJiandanDeShijie/img/annotator-glyph-sprite.png
MarkdownJiandanDeShijie/img/annotator-icon-sprite.png
MarkdownJiandanDeShijie/img/apple-touch-icon.png
MarkdownJiandanDeShijie/img/cancelfullscreen.png
MarkdownJiandanDeShijie/img/close.png
MarkdownJiandanDeShijie/img/fullscreen.png
MarkdownJiandanDeShijie/img/loader.gif
MarkdownJiandanDeShijie/img/menu-icon.png
MarkdownJiandanDeShijie/img/save.png
MarkdownJiandanDeShijie/img/saved.png
MarkdownJiandanDeShijie/img/settings-s.png
MarkdownJiandanDeShijie/img/settings.png
MarkdownJiandanDeShijie/img/star.png
MarkdownJiandanDeShijie/js/__init__.py
MarkdownJiandanDeShijie/js/epub.js
MarkdownJiandanDeShijie/js/epub.min.js
MarkdownJiandanDeShijie/js/epub.min.map
MarkdownJiandanDeShijie/js/hooks.min.js
MarkdownJiandanDeShijie/js/hooks.min.map
MarkdownJiandanDeShijie/js/reader.js
MarkdownJiandanDeShijie/js/reader.js.map
MarkdownJiandanDeShijie/js/reader.min.js
MarkdownJiandanDeShijie/js/reader.min.map
MarkdownJiandanDeShijie/js/hooks/__init__.py
MarkdownJiandanDeShijie/js/hooks/extensions/__init__.py
MarkdownJiandanDeShijie/js/hooks/extensions/highlight.js
MarkdownJiandanDeShijie/js/libs/__init__.py
MarkdownJiandanDeShijie/js/libs/jquery.min.js
MarkdownJiandanDeShijie/js/libs/localforage.min.js
MarkdownJiandanDeShijie/js/libs/screenfull.js
MarkdownJiandanDeShijie/js/libs/screenfull.min.js
markdown_jiandan_de_shijie-2024.2.29.0.dist-info/METADATA
markdown_jiandan_de_shijie-2024.2.29.0.dist-info/WHEEL
markdown_jiandan_de_shijie-2024.2.29.0.dist-info/entry_points.txt
markdown_jiandan_de_shijie-2024.2.29.0.dist-info/top_level.txt
markdown_jiandan_de_shijie-2024.2.29.0.dist-info/RECORD
